cubicweb_file/__init__.py
cubicweb_file/__pkginfo__.py
cubicweb_file/ccplugin.py
cubicweb_file/entities.py
cubicweb_file/fsimport.py
cubicweb_file/hashtools.py
cubicweb_file/hooks.py
cubicweb_file/schema.py
cubicweb_file/site_cubicweb.py
cubicweb_file/uiprops.py
cubicweb_file/data/cubes.file.css
cubicweb_file/data/cubes.file.js
cubicweb_file/data/file.png
cubicweb_file/data/icon_file.gif
cubicweb_file/data/icons/README
cubicweb_file/data/icons/application_javascript.ico
cubicweb_file/data/icons/application_pdf.ico
cubicweb_file/data/icons/application_rtf.ico
cubicweb_file/data/icons/application_vnd.ms-excel.ico
cubicweb_file/data/icons/application_vnd.ms-powerpoint.ico
cubicweb_file/data/icons/application_word.ico
cubicweb_file/data/icons/application_x-msdos-program.ico
cubicweb_file/data/icons/application_xml.ico
cubicweb_file/data/icons/application_zip.ico
cubicweb_file/data/icons/audio.ico
cubicweb_file/data/icons/audio_mpeg.ico
cubicweb_file/data/icons/audio_x-ms-wma.ico
cubicweb_file/data/icons/audio_x-wav.ico
cubicweb_file/data/icons/default.ico
cubicweb_file/data/icons/image.ico
cubicweb_file/data/icons/image_gif.ico
cubicweb_file/data/icons/image_jpeg.ico
cubicweb_file/data/icons/image_png.ico
cubicweb_file/data/icons/image_x-ms-bmp.ico
cubicweb_file/data/icons/text.ico
cubicweb_file/data/icons/text_css.ico
cubicweb_file/data/icons/text_html.ico
cubicweb_file/data/icons/video.ico
cubicweb_file/data/icons/video_mpeg.ico
cubicweb_file/data/icons/video_quicktime.ico
cubicweb_file/data/icons/video_x-ms-wmv.ico
cubicweb_file/data/icons/video_x-msvideo.ico
cubicweb_file/i18n/en.po
cubicweb_file/i18n/fr.po
cubicweb_file/migration/1.10.3_Any.py
cubicweb_file/migration/1.14.0_Any.py
cubicweb_file/migration/1.16.0_Any.py
cubicweb_file/migration/1.17.0_Any.py
cubicweb_file/migration/1.9.0_Any.py
cubicweb_file/migration/2.1.0_Any.py
cubicweb_file/migration/postcreate.py
cubicweb_file/views/__init__.py
cubicweb_file/views/gallery.py
cubicweb_file/views/urlrewrite.py
cubicweb_file-4.2.0.dist-info/METADATA
cubicweb_file-4.2.0.dist-info/WHEEL
cubicweb_file-4.2.0.dist-info/entry_points.txt
cubicweb_file-4.2.0.dist-info/top_level.txt
cubicweb_file-4.2.0.dist-info/RECORD
